{
	"restEmp": [
		{
			"id": 1,
			"first_name": "Josianne",
			"last_name": "Friesen",
			"email": "Marisa42@gmail.com"
		},
		{
			"id": 2,
			"first_name": "Monica",
			"last_name": "Borer",
			"email": "Elinore71@gmail.com"
		},
		{
			"id": 3,
			"first_name": "Anissa",
			"last_name": "Von",
			"email": "Colby38@yahoo.com"
		},
		{
			"id": 4,
			"first_name": "Kallie",
			"last_name": "Stamm",
			"email": "Kiara_Stoltenberg72@gmail.com"
		},
		{
			"id": 5,
			"first_name": "Maxwell",
			"last_name": "Rippin",
			"email": "Delilah_Dibbert58@yahoo.com"
		},
		{
			"id": 6,
			"first_name": "Stephanie",
			"last_name": "Rosenbaum",
			"email": "Zachary5@gmail.com"
		},
		{
			"id": 7,
			"first_name": "America",
			"last_name": "Grant",
			"email": "Ebony.Leffler@gmail.com"
		},
		{
			"id": 8,
			"first_name": "Giovanna",
			"last_name": "Rice",
			"email": "Leif_Veum@yahoo.com"
		},
		{
			"id": 9,
			"first_name": "Nathanael",
			"last_name": "Collins",
			"email": "Monserrat68@gmail.com"
		},
		{
			"id": 10,
			"first_name": "Clarabelle",
			"last_name": "Berge",
			"email": "Forest46@yahoo.com"
		}
	]
}